__init__.py
cprp/__init__.py
cprp/__main__.py
cprp/cli.py
cprp/utils/__init__.py
cprp/utils/default.gitignore
cprp/utils/get_content_of_files.py
cprp/utils/gitignore_parser.py
cprp/utils/parse_directory.py
cprp/utils/scan_directory.py
cprp/utils/to_tree.py
cprp-0.0.3.dist-info/LICENSE
cprp-0.0.3.dist-info/METADATA
cprp-0.0.3.dist-info/WHEEL
cprp-0.0.3.dist-info/entry_points.txt
cprp-0.0.3.dist-info/top_level.txt
cprp-0.0.3.dist-info/RECORD
