Metadata-Version: 2.2
Name: cprp
Version: 0.0.3
Summary: A command-line tool designed to help users easily convert a directory into an LLM-friendly format directly to your clipboard.
Author-email: An Jie Lee <anjie.wav@gmail.com>
License: MIT License
Project-URL: Homepage, https://github.com/danleeaj/cprp
Project-URL: Issues, https://github.com/danleeaj/cprp/issues
Classifier: Programming Language :: Python :: 3
Classifier: Operating System :: OS Independent
Requires-Python: >=3.8
License-File: LICENSE
Requires-Dist: pyperclip==1.9.0
Requires-Dist: pathspec==0.12.1
Requires-Dist: typer==0.15.2
